{
  "db_name": "PostgreSQL",
  "query": "\n            SELECT\n                epoch,\n                covers_seq,\n                nonce AS \"nonce: Nonce\",\n                ciphertext,\n                signature AS \"signature: Signature\"\n            FROM snapshots\n            WHERE list_id = $1\n            ",
  "describe": {
    "columns": [
      {
        "ordinal": 0,
        "name": "epoch",
        "type_info": "Int8",
        "origin": {
          "Table": {
            "table": "snapshots",
            "name": "epoch"
          }
        }
      },
      {
        "ordinal": 1,
        "name": "covers_seq",
        "type_info": "Int8",
        "origin": {
          "Table": {
            "table": "snapshots",
            "name": "covers_seq"
          }
        }
      },
      {
        "ordinal": 2,
        "name": "nonce: Nonce",
        "type_info": "Bytea",
        "origin": {
          "Table": {
            "table": "snapshots",
            "name": "nonce"
          }
        }
      },
      {
        "ordinal": 3,
        "name": "ciphertext",
        "type_info": "Bytea",
        "origin": {
          "Table": {
            "table": "snapshots",
            "name": "ciphertext"
          }
        }
      },
      {
        "ordinal": 4,
        "name": "signature: Signature",
        "type_info": "Bytea",
        "origin": {
          "Table": {
            "table": "snapshots",
            "name": "signature"
          }
        }
      }
    ],
    "parameters": {
      "Left": [
        "Bytea"
      ]
    },
    "nullable": [
      false,
      false,
      false,
      false,
      false
    ]
  },
  "hash": "c69ae0b4e86288d806bd3de53707a065cbeb2252c96e51394f7056609606b7d2"
}
